airtop_core/__init__.py
airtop_core/_base_client.py
airtop_core/_client.py
airtop_core/_compat.py
airtop_core/_constants.py
airtop_core/_exceptions.py
airtop_core/_files.py
airtop_core/_models.py
airtop_core/_qs.py
airtop_core/_resource.py
airtop_core/_response.py
airtop_core/_streaming.py
airtop_core/_types.py
airtop_core/_version.py
airtop_core/py.typed
airtop_core/_utils/__init__.py
airtop_core/_utils/_logs.py
airtop_core/_utils/_proxy.py
airtop_core/_utils/_reflection.py
airtop_core/_utils/_streams.py
airtop_core/_utils/_sync.py
airtop_core/_utils/_transform.py
airtop_core/_utils/_typing.py
airtop_core/_utils/_utils.py
airtop_core/lib/.keep
airtop_core/resources/__init__.py
airtop_core/resources/automations.py
airtop_core/resources/files.py
airtop_core/resources/profile.py
airtop_core/resources/requests.py
airtop_core/resources/sessions.py
airtop_core/resources/windows.py
airtop_core/types/__init__.py
airtop_core/types/automation_update_description_params.py
airtop_core/types/file_create_file_params.py
airtop_core/types/profile_delete_params.py
airtop_core/types/profile_rename_params.py
airtop_core/types/session_create_params.py
airtop_core/types/session_get_events_params.py
airtop_core/types/session_get_events_response.py
airtop_core/types/session_list_params.py
airtop_core/types/window_click_params.py
airtop_core/types/window_create_params.py
airtop_core/types/window_get_params.py
airtop_core/types/window_hover_params.py
airtop_core/types/window_load_url_params.py
airtop_core/types/window_monitor_params.py
airtop_core/types/window_page_query_params.py
airtop_core/types/window_paginated_extraction_params.py
airtop_core/types/window_prompt_content_params.py
airtop_core/types/window_scrape_params.py
airtop_core/types/window_screenshot_params.py
airtop_core/types/window_scroll_params.py
airtop_core/types/window_summarize_params.py
airtop_core/types/window_type_params.py
airtop_core/types/shared/__init__.py
airtop_core/types/shared/ai_prompt_response.py
airtop_core-0.1.0a4.dist-info/METADATA
airtop_core-0.1.0a4.dist-info/WHEEL
airtop_core-0.1.0a4.dist-info/licenses/LICENSE
airtop_core-0.1.0a4.dist-info/RECORD
